{
    "Вы профессиональный музыкант?": {
        "Нет": 8,
        "Да": 2
    },
    "У вас есть муз. образование?": {
        "Да": 5,
        "Нет": 5
    },
    "Вы играете в коллективе ? ": {
        "Нет": 6,
        "Да": 4
    },
    "Вы предпочитаете аккустику или электронику?": {
        "Аккустика": 6,
        "Электроника": 4
    },
    "Аккустика или Классика?": {
        "Аккустика": 4,
        "Классика": 2
    },
    "Вы в среднем играете больше 8 часов в неделю?": {
        "Нет": 6,
        "Да": 4
    },
    "Вам нравится мерч?": {
        "Нет": 4,
        "Да": 6
    },
    "Играете ли вы на нескольких инструментах?": {
        "Да": 4,
        "Нет": 6
    },
    "Бас или Электро?": {
        "Электро": 2,
        "Бас": 2
    },
    "Вам нравятся педали?": {
        "Да": 3,
        "Нет": 1
    }
}